LICENSE.TXT
README.md
setup.py
ngclib/__init__.py
ngclib/logger.py
ngclib.egg-info/PKG-INFO
ngclib.egg-info/SOURCES.txt
ngclib.egg-info/dependency_links.txt
ngclib.egg-info/requires.txt
ngclib.egg-info/top_level.txt
ngclib/evaluation/__init__.py
ngclib/evaluation/compute_metrics_iteration.py
ngclib/evaluation/export_iteration_predictions.py
ngclib/evaluation/node_metrics_loco.py
ngclib/graph_cfg/__init__.py
ngclib/graph_cfg/build_model_from_cfg.py
ngclib/graph_cfg/graph_cfg.py
ngclib/models/__init__.py
ngclib/models/base_ngc_model.py
ngclib/models/build_model.py
ngclib/models/ngc.py
ngclib/models/ngc_ensemble.py
ngclib/models/ngc_hyperedges.py
ngclib/models/ngc_v1.py
ngclib/models/edges/__init__.py
ngclib/models/edges/ensemble_edge.py
ngclib/models/edges/hyper_edge.py
ngclib/models/edges/ngc_edge.py
ngclib/models/edges/single_link.py
ngclib/models/edges/two_hop_link.py
ngclib/ngcdir/__init__.py
ngclib/ngcdir/ngcdir.py
ngclib/ngcdir/ngcdir_status.py
ngclib/readers/__init__.py
ngclib/readers/clone_dim_reader.py
ngclib/readers/edge_reader.py
ngclib/readers/graph_reader.py
ngclib/readers/ngc_npz_reader.py
ngclib/readers/utils.py
ngclib/semisupervised/__init__.py
ngclib/semisupervised/semisup.py
ngclib/semisupervised/train_set.py
ngclib/trainer/__init__.py
ngclib/trainer/callbacks.py
ngclib/trainer/ngc_trainer.py
ngclib/trainer/trainable_ngc.py
ngclib/trainer/utils.py
ngclib/trainer/iteration_trainer/__init__.py
ngclib/trainer/iteration_trainer/base_iteration_trainer.py
ngclib/trainer/iteration_trainer/parallel_trainer.py
ngclib/trainer/iteration_trainer/sequential_trainer.py
ngclib/utils/__init__.py
ngclib/utils/deterministic_augmentation.py
ngclib/utils/dir_linker.py
ngclib/utils/export_pseudolabels.py
ngclib/utils/ngc_augmentation.py
ngclib/utils/nodes_importer.py
ngclib/utils/types.py
ngclib/utils/utils.py