Metadata-Version: 2.1
Name: ngclib
Version: 0.5
Summary: NGC Library
Home-page: https://gitlab.com/neural-graph-consensus/ngclib
License: WTFPL
Platform: UNKNOWN
Requires-Python: >=3.8
License-File: LICENSE.TXT
